{
  "hunt_code": "PB5065",
  "species": "Pronghorn",
  "hunt_name": "Fillmore, Oak Creek South",
  "hunt_type": "Limited Entry",
  "weapon": "Muzzleloader",
  "sex_type": "Male Only",
  "access_type": "Public",
  "permits_total": 15,
  "hunters": 14,
  "harvest": 11,
  "percent_success": 78.6,
  "avg_days": 3,
  "satisfaction": 4.2,
  "has_harvest": true,
  "has_bonus_draw": false,
  "has_antlerless_draw": false,
  "draw_family": "none",
  "draw_presence_flag": "no",
  "score_family": "public_general",
  "public_rank_eligible": "yes",
  "draw_difficulty_flag": "",
  "resident_point_signal": null,
  "nonresident_point_signal": null,
  "harvest_success_score": 78.6,
  "harvest_pressure_score": 0.9333,
  "harvest_efficiency_score": 0.7857,
  "scoring_notes": "Public hunt with harvest-only/general structure; success=78.6; pressure=hunters/permits=0.9333; efficiency=harvest/hunters=0.7857; no draw-source signal; score_family=public_general",
  "draw_access_score": null,
  "verified_outfitter_count": 30,
  "cpo_outfitter_count": 0,
  "dwr_boundary_link": "https://dwrapps.utah.gov/huntboundary/hbstart?HN=PB5065",
  "dwr_source_guide": "Pronghorn workbook",
  "dwr_unit_name": "Fillmore, Oak Creek South",
  "recommended_permits": {
    "recommendation_year": 2026,
    "permit_category": "2026 Buck Pronghorn Permit Recommendations",
    "section_title": "Pronghorn Buck",
    "hunt_name": "Fillmore, Oak Creek South",
    "weapon": "Muzzleloader",
    "sex_type": "Buck",
    "access_class": "Public",
    "resident_permits": 15,
    "nonresident_permits": 2,
    "total_permits": 17,
    "resident_permits_prior": 13,
    "nonresident_permits_prior": 2,
    "total_permits_prior": 15,
    "source_page_number": null,
    "source_type": "pronghorn_buck_workbook",
    "source_authority_level": "updated_current_permits"
  },
  "bonus_draw": null,
  "antlerless_draw": null,
  "projected_bonus_draw": null
}